setup.py
ddshell/__init__.py
ddshell/dd.py
ddshell/utils.py
ddshell.egg-info/PKG-INFO
ddshell.egg-info/SOURCES.txt
ddshell.egg-info/dependency_links.txt
ddshell.egg-info/entry_points.txt
ddshell.egg-info/top_level.txt