Metadata-Version: 2.2
Name: ddshell
Version: 0.0.9
Summary: shell菜单
Home-page: https://gitee.com/chenddcoder/ddshell
Author: chenddcoder
Author-email: chenddcoder@foxmail.com
License: MIT Licence
Keywords: shell,menu,ddshell,ddmenu
Platform: any
Dynamic: author
Dynamic: author-email
Dynamic: description
Dynamic: home-page
Dynamic: keywords
Dynamic: license
Dynamic: platform
Dynamic: summary
